simple_top.sv
// This file is public domain, it can be freely copied without restrictions.
// SPDX-License-Identifier: CC0-1.0

`timescale 1us/1us

module top();
  logic clk = 0;
  logic din,dout;

  block block_i(clk, din, dout);

  initial begin
    forever begin
      #10 clk <= ~clk;
    end
  end
endmodule

module block (
  input logic clk, din,
  output logic dout
);

reg [10:0] ctr = 0;

always @(posedge clk) begin
  ctr <= ctr + 1;

  if (ctr !== 40)
    dout <= din;
end

assert property(@(negedge clk) din == dout);

endmodule

test/data/simple.vcd
$date
    Aug  2, 2021  02:59:08
$end
$version
    TOOL:	xmsim(64)	21.05-a001
$end
$timescale
    1 us
$end

$scope module top $end
$var reg       1 !    clk $end
$var reg       1 "    din $end
$var reg       1 #    dout $end

$scope module block_i $end
$var wire      1 $    clk  $end
$var wire      1 %    din  $end
$var reg       1 &    dout $end
$var reg      11 '    ctr [10:0] $end
$upscope $end

$upscope $end

$enddefinitions $end
$dumpvars
0!
1"
x#
0$
1%
x&
b0 '
$end
#10
1!
1$
b1 '
1&
1#
#20
0!
0$
#30
1!
1$
b10 '
#40
0!
0$
#50
1!
1$
b11 '
#60
0!
0$
#70
1!
1$
b100 '
#80
0!
0$
0"
0%
#90
1!
1$
b101 '
0&
0#
#100
0!
0$
1"
1%
#110
1!
1$
b110 '
1&
1#
#120
0!
0$
0"
0%
#130
1!
1$
b111 '
0&
0#
#140
0!
0$
1"
1%
#150
1!
1$
b1000 '
1&
1#
#160
0!
0$
0"
0%
#170
1!
1$
b1001 '
0&
0#
#180
0!
0$
1"
1%
#190
1!
1$
b1010 '
1&
1#
#200
0!
0$
#210
1!
1$
b1011 '
#220
0!
0$
0"
0%
#230
1!
1$
b1100 '
0&
0#
#240
0!
0$
#250
1!
1$
b1101 '
#260
0!
0$
#270
1!
1$
b1110 '
#280
0!
0$
1"
1%
#290
1!
1$
b1111 '
1&
1#
#300
0!
0$
0"
0%
#310
1!
1$
b10000 '
0&
0#
#320
0!
0$
1"
1%
#330
1!
1$
b10001 '
1&
1#
#340
0!
0$
0"
0%
#350
1!
1$
b10010 '
0&
0#
#360
0!
0$
1"
1%
#370
1!
1$
b10011 '
1&
1#
#380
0!
0$
0"
0%
#390
1!
1$
b10100 '
0&
0#
#400
0!
0$
1"
1%
#410
1!
1$
b10101 '
1&
1#
#420
0!
0$
0"
0%
#430
1!
1$
b10110 '
0&
0#
#440
0!
0$
#450
1!
1$
b10111 '
#460
0!
0$
1"
1%
#470
1!
1$
b11000 '
1&
1#
#480
0!
0$
#490
1!
1$
b11001 '
#500
0!
0$
0"
0%
#510
1!
1$
b11010 '
0&
0#
#520
0!
0$
#530
1!
1$
b11011 '
#540
0!
0$
1"
1%
#550
1!
1$
b11100 '
1&
1#
#560
0!
0$
#570
1!
1$
b11101 '
#580
0!
0$
#590
1!
1$
b11110 '
#600
0!
0$
#610
1!
1$
b11111 '
#620
0!
0$
0"
0%
#630
1!
1$
b100000 '
0&
0#
#640
0!
0$
1"
1%
#650
1!
1$
b100001 '
1&
1#
#660
0!
0$
#670
1!
1$
b100010 '
#680
0!
0$
0"
0%
#690
1!
1$
b100011 '
0&
0#
#700
0!
0$
#710
1!
1$
b100100 '
#720
0!
0$
#730
1!
1$
b100101 '
#740
0!
0$
1"
1%
#750
1!
1$
b100110 '
1&
1#
#760
0!
0$
0"
0%
#770
1!
1$
b100111 '
0&
0#
#780
0!
0$
1"
1%
#790
1!
1$
b101000 '
1&
1#
#800
0!
0$
0"
0%
#810
1!
1$
b101001 '
#820
0!
0$
#830
1!
1$
b101010 '
0&
0#
#840
0!
0$
#850
1!
1$
b101011 '
#860
0!
0$
#870
1!
1$
b101100 '
#880
0!
0$
#890
1!
1$
b101101 '
#900
0!
0$
#910
1!
1$
b101110 '
#920
0!
0$
1"
1%
#930
1!
1$
b101111 '
1&
1#
#940
0!
0$
#950
1!
1$
b110000 '
#960
0!
0$
#970
1!
1$
b110001 '
#980
0!
0$
0"
0%
#990
1!
1$
b110010 '
0&
0#
#1000
0!
0$
#1010
1!
1$
b110011 '
#1020
0!
0$
#1030
1!
1$
b110100 '
#1040
0!
0$
#1050
1!
1$
b110101 '
#1060
0!
0$
#1070
1!
1$
b110110 '
#1080
0!
0$
#1090
1!
1$
b110111 '
#1100
0!
0$
#1110
1!
1$
b111000 '
#1120
0!
0$
1"
1%
#1130
1!
1$
b111001 '
1&
1#
#1140
0!
0$
0"
0%
#1150
1!
1$
b111010 '
0&
0#
#1160
0!
0$
#1170
1!
1$
b111011 '
#1180
0!
0$
1"
1%
#1190
1!
1$
b111100 '
1&
1#
#1200
0!
0$
0"
0%
#1210
1!
1$
b111101 '
0&
0#
#1220
0!
0$
1"
1%
#1230
1!
1$
b111110 '
1&
1#
#1240
0!
0$
#1250
1!
1$
b111111 '
#1260
0!
0$
#1270
1!
1$
b1000000 '
#1280
0!
0$
0"
0%
#1290
1!
1$
b1000001 '
0&
0#
#1300
0!
0$
#1310
1!
1$
b1000010 '
#1320
0!
0$
#1330
1!
1$
b1000011 '
#1340
0!
0$
#1350
1!
1$
b1000100 '
#1360
0!
0$
#1370
1!
1$
b1000101 '
#1380
0!
0$
1"
1%
#1390
1!
1$
b1000110 '
1&
1#
#1400
0!
0$
0"
0%
#1410
1!
1$
b1000111 '
0&
0#
#1420
0!
0$
#1430
1!
1$
b1001000 '
#1440
0!
0$
1"
1%
#1450
1!
1$
b1001001 '
1&
1#
#1460
0!
0$
#1470
1!
1$
b1001010 '
#1480
0!
0$
0"
0%
#1490
1!
1$
b1001011 '
0&
0#
#1500
0!
0$
1"
1%
#1510
1!
1$
b1001100 '
1&
1#
#1520
0!
0$
0"
0%
#1530
1!
1$
b1001101 '
0&
0#
#1540
0!
0$
1"
1%
#1550
1!
1$
b1001110 '
1&
1#
#1560
0!
0$
#1570
1!
1$
b1001111 '
#1580
0!
0$
#1590
1!
1$
b1010000 '
#1600
0!
0$
#1610
1!
1$
b1010001 '
#1620
0!
0$
0"
0%
#1630
1!
1$
b1010010 '
0&
0#
#1640
0!
0$
#1650
1!
1$
b1010011 '
#1660
0!
0$
#1670
1!
1$
b1010100 '
#1680
0!
0$
1"
1%
#1690
1!
1$
b1010101 '
1&
1#
#1700
0!
0$
#1710
1!
1$
b1010110 '
#1720
0!
0$
0"
0%
#1730
1!
1$
b1010111 '
0&
0#
#1740
0!
0$
1"
1%
#1750
1!
1$
b1011000 '
1&
1#
#1760
0!
0$
#1770
1!
1$
b1011001 '
#1780
0!
0$
#1790
1!
1$
b1011010 '
#1800
0!
0$
#1810
1!
1$
b1011011 '
#1820
0!
0$
#1830
1!
1$
b1011100 '
#1840
0!
0$
#1850
1!
1$
b1011101 '
#1860
0!
0$
0"
0%
#1870
1!
1$
b1011110 '
0&
0#
#1880
0!
0$
#1890
1!
1$
b1011111 '
#1900
0!
0$
1"
1%
#1910
1!
1$
b1100000 '
1&
1#
#1920
0!
0$
#1930
1!
1$
b1100001 '
#1940
0!
0$
0"
0%
#1950
1!
1$
b1100010 '
0&
0#
#1960
0!
0$
1"
1%
#1970
1!
1$
b1100011 '
1&
1#
#1980
0!
0$
#1990
1!
1$
b1100100 '
