simple_top.sv
// This file is public domain, it can be freely copied without restrictions.
// SPDX-License-Identifier: CC0-1.0

`timescale 1us/1us

module top();
  logic clk = 0;
  logic din,dout;

  block block_i(clk, din, dout);

  initial begin
    forever begin
      #10 clk <= ~clk;
    end
  end
endmodule

module block (
  input logic clk, din,
  output logic dout
);

reg [10:0] ctr = 0;

always @(posedge clk) begin
  ctr <= ctr + 1;

  if (ctr !== 40)
    dout <= din;
end

assert property(@(negedge clk) din == dout);

endmodule

wave/vcd_script/sample.vcd
$date
	Mon Jul 19 00:17:28 2021

$end
$version
	Chronologic Simulation VCS Release Q-2020.03-SP2-2_Full64
$end
$timescale
	1us
$end
$scope module top $end
$var reg 1 ! clk $end
$var reg 1 " din $end
$var reg 1 # dout $end
$scope module block_i $end
$var reg 1 $ din $end
$var reg 1 % dout $end
$var reg 1 & clk $end
$var reg 11 ' ctr [10:0] $end
$upscope $end
$upscope $end
$enddefinitions $end
$dumpvars
0!
b00000000000 '
0"
0$
x%
x#
0&
$end
#10
0#
1&
1!
b00000000001 '
0%
#20
0&
1"
0!
1$
#30
1!
1%
b00000000010 '
1#
1&
#40
0!
0&
#50
1!
1&
b00000000011 '
#60
0&
0$
0!
0"
#70
1!
b00000000100 '
0#
0%
1&
#80
0!
0&
#90
b00000000101 '
1&
1!
#100
1$
0!
1"
0&
#110
b00000000110 '
1&
1%
1!
1#
#120
0!
0&
#130
b00000000111 '
1&
1!
#140
0$
0!
0"
0&
#150
0#
1&
b00000001000 '
1!
0%
#160
0!
1$
1"
0&
#170
1!
1&
1#
1%
b00000001001 '
#180
0&
0!
#190
1&
1!
b00000001010 '
#200
0!
0&
#210
1!
1&
b00000001011 '
#220
0&
0!
#230
1&
1!
b00000001100 '
#240
0!
0$
0"
0&
#250
1!
1&
b00000001101 '
0%
0#
#260
0&
1"
0!
1$
#270
1!
1&
1%
1#
b00000001110 '
#280
0&
0$
0!
0"
#290
1!
1&
0#
b00000001111 '
0%
#300
0&
0!
#310
1&
1!
b00000010000 '
#320
0!
0&
#330
1!
1&
b00000010001 '
#340
0&
1"
1$
0!
#350
1&
1!
1%
b00000010010 '
1#
#360
0!
0$
0&
0"
#370
1&
1!
b00000010011 '
0#
0%
#380
0!
0&
#390
1!
1&
b00000010100 '
#400
0&
1"
0!
1$
#410
1!
b00000010101 '
1%
1#
1&
#420
0!
0&
#430
b00000010110 '
1&
1!
#440
0&
0!
#450
1&
1!
b00000010111 '
#460
0!
0"
0$
0&
#470
1!
1&
b00000011000 '
0#
0%
#480
0&
0!
#490
1&
1!
b00000011001 '
#500
0!
1$
0&
1"
#510
1&
b00000011010 '
1%
1#
1!
#520
0&
0!
#530
b00000011011 '
1!
1&
#540
0$
0&
0"
0!
#550
b00000011100 '
1!
0#
1&
0%
#560
0&
0!
#570
b00000011101 '
1!
1&
#580
0!
0&
#590
1!
1&
b00000011110 '
#600
0&
1$
1"
0!
#610
1&
1!
1%
b00000011111 '
1#
#620
0!
0&
#630
1!
1&
b00000100000 '
#640
0&
0!
#650
1&
1!
b00000100001 '
#660
0!
0&
#670
1!
1&
b00000100010 '
#680
0&
0"
0$
0!
#690
1&
1!
0#
b00000100011 '
0%
#700
0!
0&
#710
1!
1&
b00000100100 '
#720
0&
1$
1"
0!
#730
1&
1!
1%
b00000100101 '
1#
#740
0!
0&
#750
1!
1&
b00000100110 '
#760
0&
0!
#770
1&
1!
b00000100111 '
#780
0!
0&
#790
1!
1&
b00000101000 '
#800
0&
0!
#810
1&
1!
b00000101001 '
#820
0!
0"
0$
0&
#830
1!
1&
0#
b00000101010 '
0%
#840
0&
0!
#850
1&
1!
b00000101011 '
#860
0!
1$
1"
0&
#870
1!
1&
1%
b00000101100 '
1#
#880
0&
0"
0!
0$
#890
1!
1&
b00000101101 '
0#
0%
#900
0&
1$
0!
1"
#910
1!
1&
1#
1%
b00000101110 '
#920
0&
0"
0!
0$
#930
1!
1&
0%
b00000101111 '
0#
#940
0&
1$
0!
1"
#950
1!
1&
b00000110000 '
1#
1%
#960
0&
0!
#970
1&
1!
b00000110001 '
#980
0!
0&
#990
1!
1&
b00000110010 '
#1000
0&
0"
0!
0$
#1010
1!
b00000110011 '
0%
0#
1&
#1020
0!
0&
#1030
b00000110100 '
1&
1!
#1040
1"
0!
1$
0&
#1050
b00000110101 '
1&
1#
1!
1%
#1060
0!
0&
#1070
b00000110110 '
1&
1!
#1080
0&
0!
#1090
1&
1!
b00000110111 '
#1100
0!
0"
0$
0&
#1110
1!
1&
0%
b00000111000 '
0#
#1120
0&
1$
0!
1"
#1130
1!
1&
b00000111001 '
1#
1%
#1140
0&
0!
#1150
1&
1!
b00000111010 '
#1160
0!
0&
#1170
1!
1&
b00000111011 '
#1180
0&
0"
0!
0$
#1190
1!
b00000111100 '
0%
0#
1&
#1200
0!
0&
#1210
b00000111101 '
1&
1!
#1220
0&
0!
#1230
1&
1!
b00000111110 '
#1240
0!
0&
#1250
1!
1&
b00000111111 '
#1260
0&
0!
#1270
1&
1!
b00001000000 '
#1280
0!
0&
#1290
1!
1&
b00001000001 '
#1300
0&
1"
1$
0!
#1310
1&
1!
b00001000010 '
1#
1%
#1320
0!
0&
#1330
1!
1&
b00001000011 '
#1340
0&
0!
#1350
1&
1!
b00001000100 '
#1360
0!
0&
#1370
1!
1&
b00001000101 '
#1380
0&
0$
0!
0"
#1390
1!
b00001000110 '
0%
0#
1&
#1400
0!
0&
#1410
b00001000111 '
1&
1!
#1420
0&
0!
#1430
1&
1!
b00001001000 '
#1440
0!
1$
1"
0&
#1450
1!
1&
b00001001001 '
1#
1%
#1460
0&
0!
#1470
1&
1!
b00001001010 '
#1480
0!
0"
0&
0$
#1490
1&
b00001001011 '
0%
0#
1!
#1500
0&
0!
#1510
b00001001100 '
1!
1&
#1520
1"
0&
1$
0!
#1530
b00001001101 '
1!
1#
1&
1%
#1540
0&
0!
#1550
b00001001110 '
1!
1&
#1560
0!
0&
#1570
1!
1&
b00001001111 '
#1580
0&
0"
0$
0!
#1590
1&
1!
0%
b00001010000 '
0#
#1600
0!
1$
0&
1"
#1610
1&
1!
b00001010001 '
1#
1%
#1620
0!
0"
0&
0$
#1630
1&
1!
0#
0%
b00001010010 '
#1640
0!
1$
0&
1"
#1650
1&
1!
1%
b00001010011 '
1#
#1660
0!
0"
0&
0$
#1670
1&
1!
b00001010100 '
0#
0%
#1680
0!
1$
0&
1"
#1690
1&
1!
1#
1%
b00001010101 '
#1700
0!
0&
#1710
1!
1&
b00001010110 '
#1720
0&
0$
0"
0!
#1730
1&
1!
b00001010111 '
0%
0#
#1740
0!
0&
#1750
1!
1&
b00001011000 '
#1760
0&
0!
#1770
1&
1!
b00001011001 '
#1780
0!
1"
0&
1$
#1790
1&
b00001011010 '
1#
1%
1!
#1800
0$
0!
0&
0"
#1810
1&
b00001011011 '
0%
1!
0#
#1820
0&
0!
#1830
b00001011100 '
1!
1&
#1840
0!
0&
#1850
1!
1&
b00001011101 '
#1860
0&
1$
1"
0!
#1870
1&
1!
1#
b00001011110 '
1%
#1880
0!
0"
0&
0$
#1890
1&
1!
b00001011111 '
0%
0#
#1900
0!
0&
#1910
1!
1&
b00001100000 '
#1920
0&
1$
0!
1"
#1930
1!
b00001100001 '
1#
1%
1&
#1940
0"
0&
0!
0$
#1950
1!
b00001100010 '
0%
1&
0#
#1960
0!
0&
#1970
b00001100011 '
1&
1!
#1980
1"
0!
1$
0&
#1990
b00001100100 '
1&
1#
1%
1!
